mpl_pan_zoom/__init__.py
mpl_pan_zoom/_pan.py
mpl_pan_zoom/_zoom.py
mpl_pan_zoom-1.1.0.dist-info/METADATA
mpl_pan_zoom-1.1.0.dist-info/WHEEL
mpl_pan_zoom-1.1.0.dist-info/licenses/LICENSE
mpl_pan_zoom-1.1.0.dist-info/RECORD
